hifiscan/__init__.py
hifiscan/__main__.py
hifiscan/analyzer.py
hifiscan/app.py
hifiscan/audio.py
hifiscan/io_.py
hifiscan-1.5.2.dist-info/LICENSE
hifiscan-1.5.2.dist-info/METADATA
hifiscan-1.5.2.dist-info/WHEEL
hifiscan-1.5.2.dist-info/entry_points.txt
hifiscan-1.5.2.dist-info/top_level.txt
hifiscan-1.5.2.dist-info/RECORD
