Metadata-Version: 2.1
Name: hifiscan
Version: 1.5.2
Summary: Optimize the audio quality of loudspeakers
Home-page: https://github.com/erdewit/hifiscan
Author: Ewald R. de Wit
Author-email: ewald.de.wit@gmail.com
License: BSD
Keywords: frequency impulse response audio spectrum equalizer
Classifier: Development Status :: 5 - Production/Stable
Classifier: Intended Audience :: End Users/Desktop
Classifier: Topic :: Multimedia :: Sound/Audio :: Analysis
Classifier: License :: OSI Approved :: BSD License
Classifier: Programming Language :: Python :: 3.8
Classifier: Programming Language :: Python :: 3.9
Classifier: Programming Language :: Python :: 3.10
Classifier: Programming Language :: Python :: 3.11
Classifier: Programming Language :: Python :: 3.12
Classifier: Programming Language :: Python :: 3 :: Only
Requires-Python: >=3.8
License-File: LICENSE
Requires-Dist: eventkit
Requires-Dist: numpy
Requires-Dist: PyQt6
Requires-Dist: pyqtgraph
Requires-Dist: sounddevice
